CHANGES.txt
COPYRIGHT.txt
LICENSE.txt
README.txt
TODO.txt
bootstrap.py
buildout.cfg
setup.py
speedtest.py
3rdparty/SimpleParse-2.1.0a1.tar.gz
src/gocept/__init__.py
src/gocept.objectquery.egg-info/PKG-INFO
src/gocept.objectquery.egg-info/SOURCES.txt
src/gocept.objectquery.egg-info/dependency_links.txt
src/gocept.objectquery.egg-info/namespace_packages.txt
src/gocept.objectquery.egg-info/not-zip-safe
src/gocept.objectquery.egg-info/requires.txt
src/gocept.objectquery.egg-info/top_level.txt
src/gocept/objectquery/__init__.py
src/gocept/objectquery/collection.py
src/gocept/objectquery/collection.txt
src/gocept/objectquery/indexsupport.py
src/gocept/objectquery/indexsupport.txt
src/gocept/objectquery/interfaces.py
src/gocept/objectquery/interfaces.txt
src/gocept/objectquery/pathexpressions.py
src/gocept/objectquery/pathexpressions.txt
src/gocept/objectquery/processor.py
src/gocept/objectquery/processor.txt
src/gocept/objectquery/querysupport.py
src/gocept/objectquery/querysupport.txt
src/gocept/objectquery/testobjects.py
src/gocept/objectquery/tests.py