Metadata-Version: 1.0
Name: gocept.objectquery
Version: 0.1a2
Summary: A framework for indexing and querying the ZODB
Home-page: https://intra.gocept.com/projects/projects/show/objectquery
Author: Sebastian Wehrmann
Author-email: sw@gocept.com
License: ZPL 2.1
Platform: UNKNOWN
Classifier: Development Status :: 2 - Pre-Alpha
Classifier: Intended Audience :: Developers
Classifier: License :: OSI Approved :: Zope Public License
Classifier: Programming Language :: Python
Classifier: Natural Language :: English
Classifier: Operating System :: OS Independent
Classifier: Topic :: Database
